prodoco/__init__.py
prodoco/discovery.py
prodoco/logger.py
prodoco-0.0.2.dist-info/LICENSE
prodoco-0.0.2.dist-info/METADATA
prodoco-0.0.2.dist-info/WHEEL
prodoco-0.0.2.dist-info/entry_points.txt
prodoco-0.0.2.dist-info/RECORD
