Metadata-Version: 2.1
Name: prodoco
Version: 0.0.2
Summary: Prometheus service discovery for Docker Compose
Home-page: https://github.com/Ch00k/prodoco
License: MIT
Author: Andrii Yurchuk
Author-email: ay@mntw.re
Requires-Python: >=3.12,<4.0
Classifier: License :: OSI Approved :: MIT License
Classifier: Programming Language :: Python :: 3
Classifier: Programming Language :: Python :: 3.12
Classifier: Programming Language :: Python :: 3.13
Requires-Dist: apscheduler (>=3.11.0,<4.0.0)
Requires-Dist: click (>=8.1.8,<9.0.0)
Requires-Dist: docker (>=7.1.0,<8.0.0)
Requires-Dist: pytest-cov (>=6.0.0,<7.0.0)
Requires-Dist: ruamel-yaml (>=0.18.6,<0.19.0)
Project-URL: Repository, https://github.com/Ch00k/prodoco
